snowforge/__init__.py
snowforge/copy_into.py
snowforge/file_format.py
snowforge/forge.py
snowforge/put.py
snowforge/stage.py
snowforge/stream.py
snowforge/table.py
snowforge/task.py
snowforge/utilities.py
snowforge-0.1.0a1.dist-info/METADATA
snowforge-0.1.0a1.dist-info/WHEEL
snowforge-0.1.0a1.dist-info/licenses/LICENSE
snowforge-0.1.0a1.dist-info/RECORD
